vision_v1/__init__.py
vision_v1/envs/__init__.py
vision_v1/envs/vision_env.py
vision_v1-0.9.8.dist-info/METADATA
vision_v1-0.9.8.dist-info/WHEEL
vision_v1-0.9.8.dist-info/top_level.txt
vision_v1-0.9.8.dist-info/RECORD
