Metadata-Version: 2.1
Name: vision-v1
Version: 0.9.8
Summary: A OpenAI Gym Env for vision
Home-page: UNKNOWN
License: UNKNOWN
Platform: UNKNOWN
Requires-Dist: gym
